aiosafeconsumer/__init__.py
aiosafeconsumer/consumer.py
aiosafeconsumer/kafka.py
aiosafeconsumer/kafka_stubs.py
aiosafeconsumer/logging.py
aiosafeconsumer/logging_context.py
aiosafeconsumer/processor.py
aiosafeconsumer/py.typed
aiosafeconsumer/redis.py
aiosafeconsumer/run.py
aiosafeconsumer/source.py
aiosafeconsumer/types.py
aiosafeconsumer/worker.py
aiosafeconsumer/workerpool.py
aiosafeconsumer/datasync/__init__.py
aiosafeconsumer/datasync/base.py
aiosafeconsumer/datasync/elasticsearch.py
aiosafeconsumer/datasync/mongo.py
aiosafeconsumer/datasync/postgres.py
aiosafeconsumer/datasync/redis.py
aiosafeconsumer/datasync/types.py
aiosafeconsumer-0.0.8.dist-info/licenses/LICENSE
aiosafeconsumer-0.0.8.dist-info/METADATA
aiosafeconsumer-0.0.8.dist-info/WHEEL
aiosafeconsumer-0.0.8.dist-info/top_level.txt
aiosafeconsumer-0.0.8.dist-info/RECORD
