Metadata-Version: 2.4
Name: aiosafeconsumer
Version: 0.0.8
Summary: Safely consume and process data.
Author-email: Kostiantyn Korikov <lostclus@gmail.com>
License-Expression: BSD-2-Clause
Project-URL: Repository, http://github.com/lostclus/aiosafeconsumer
Keywords: asyncio,consumer,microservices
Classifier: Development Status :: 3 - Alpha
Classifier: Environment :: No Input/Output (Daemon)
Classifier: Framework :: AsyncIO
Classifier: Intended Audience :: Developers
Classifier: Operating System :: OS Independent
Classifier: Programming Language :: Python
Classifier: Programming Language :: Python :: 3
Classifier: Programming Language :: Python :: 3.10
Classifier: Programming Language :: Python :: 3.11
Classifier: Programming Language :: Python :: 3.12
Classifier: Programming Language :: Python :: 3.13
Classifier: Typing :: Typed
Requires-Python: >=3.10
License-File: LICENSE
Requires-Dist: croniter
Provides-Extra: kafka
Requires-Dist: aiokafka; extra == "kafka"
Provides-Extra: redis
Requires-Dist: redis[hiredis]; extra == "redis"
Provides-Extra: elasticsearch
Requires-Dist: elasticsearch[async]; extra == "elasticsearch"
Provides-Extra: mongo
Requires-Dist: pymongo; extra == "mongo"
Provides-Extra: postgres
Requires-Dist: asyncpg; extra == "postgres"
Provides-Extra: tests
Requires-Dist: aiokafka; extra == "tests"
Requires-Dist: elasticsearch[async]; extra == "tests"
Requires-Dist: pytest; extra == "tests"
Requires-Dist: pytest-asyncio; extra == "tests"
Requires-Dist: pytest-cov; extra == "tests"
Requires-Dist: redis[hiredis]; extra == "tests"
Requires-Dist: pymongo; extra == "tests"
Requires-Dist: asyncpg; extra == "tests"
Requires-Dist: asyncpg-stubs; extra == "tests"
Requires-Dist: camel-converter; extra == "tests"
Dynamic: license-file
